spatialdm/__init__.py
spatialdm/diff_utils.py
spatialdm/main.py
spatialdm/plottings.py
spatialdm/utils.py
spatialdm/version.py
spatialdm/datasets/__init__.py
spatialdm/datasets/_util_dataset.py
spatialdm/datasets/dataset.py
SpatialDM-0.2.0.dist-info/LICENSE
SpatialDM-0.2.0.dist-info/METADATA
SpatialDM-0.2.0.dist-info/WHEEL
SpatialDM-0.2.0.dist-info/top_level.txt
SpatialDM-0.2.0.dist-info/RECORD
