Metadata-Version: 2.1
Name: SpatialDM
Version: 0.2.0
Summary: SpatialDM: Spatial co-expression Detected by bivariate Moran
Home-page: https://github.com/leeyoyohku/SpatialDM
Author: ['Zhouxuan Li', 'Tianjie Wang', 'Yuanhua Huang']
Author-email: leeyoyo@connect.hku.hk
License: Apache-2.0
Keywords: Spatial transcriptomics,Spatial association,Ligand-recptor interaction
Platform: UNKNOWN
Requires-Dist: anndata (>=0.6)
Requires-Dist: scanpy (>=1.5)
Requires-Dist: SpatialDE
Requires-Dist: numpy (>=1.9.0)
Requires-Dist: scipy (>=1.4.0)
Requires-Dist: statsmodels (>=0.11)
Requires-Dist: pandas (>=0.23.0)
Requires-Dist: h5py (>=2.9.0)
Requires-Dist: matplotlib (>=3.1.2)
Requires-Dist: holoviews
Requires-Dist: seaborn
Requires-Dist: selenium
Requires-Dist: scikit-learn (>=0.23)
Requires-Dist: hilearn
Requires-Dist: threadpoolctl
Provides-Extra: docs
Requires-Dist: sphinx-bootstrap-theme ; extra == 'docs'
